{
  "predecessor": "GoalOS GJFFI Ω AGI Club GitHub Pages v10.0.0-GHP1",
  "predecessorIds": 468,
  "currentIds": 549,
  "missingPredecessorIds": [],
  "addedIds": [
    "expansion-office",
    "glArchitectureMap",
    "glBudget",
    "glCapitalNeed",
    "glCapitalStack",
    "glControl",
    "glCrossBorder",
    "glCurrency",
    "glCustomerCash",
    "glDecision",
    "glDefaults",
    "glDilution",
    "glDriftCanvas",
    "glDriftNarrative",
    "glDriftScore",
    "glEngineState",
    "glEvidence",
    "glExportBoard",
    "glExportDossier",
    "glExportJobs",
    "glExportWatch",
    "glGraphReset",
    "glHash",
    "glHorizon",
    "glInfra",
    "glInfrastructure",
    "glIntent",
    "glJobFilter",
    "glJobSearch",
    "glJobsBlocked",
    "glJobsComplete",
    "glJobsEvidence",
    "glJobsGrid",
    "glJobsTotal",
    "glMissionEdges",
    "glMissionGraph",
    "glMissionNodes",
    "glMissionSummaryText",
    "glMissionSummaryTitle",
    "glModuleList",
    "glName",
    "glOpenKernel",
    "glPreserveControl",
    "glProofDebt",
    "glPublicSupport",
    "glRD",
    "glReadiness",
    "glRegSurface",
    "glRegulated",
    "glReset",
    "glResilience",
    "glRobust",
    "glRoot",
    "glRun",
    "glRunDrift",
    "glRunway",
    "glSaveMission",
    "glScenarioName",
    "glSector",
    "glSimplicity",
    "glSimulateChange",
    "glSpeed",
    "glStage",
    "glStageRail",
    "glSupport",
    "glSupportValue",
    "glSwitches",
    "glTarget",
    "glTeam",
    "glThesis",
    "glTriggerCount",
    "glTriggers",
    "glWatchList",
    "global-launch",
    "goalos-global-launch-mobile-compat",
    "goalos-global-launch-v11-css",
    "goalos-global-launch-v11-js",
    "heroLaunchRun",
    "launch-missions",
    "launch-plan",
    "launchTypeGrid"
  ],
  "status": "PASS"
}